LICENSE
MANIFEST.in
README.md
pyproject.toml
setup.py
omnigibson/.gitignore
omnigibson/__init__.py
omnigibson/download_datasets.py
omnigibson/install.py
omnigibson/kit_file_changes.patch
omnigibson/lazy.py
omnigibson/macros.py
omnigibson/omnigibson_2023_1_1.kit
omnigibson/omnigibson_4_0_0.kit
omnigibson/omnigibson_4_1_0.kit
omnigibson/omnigibson_gym.kit
omnigibson/simulator.py
omnigibson/transition_rules.py
omnigibson.egg-info/PKG-INFO
omnigibson.egg-info/SOURCES.txt
omnigibson.egg-info/dependency_links.txt
omnigibson.egg-info/not-zip-safe
omnigibson.egg-info/requires.txt
omnigibson.egg-info/top_level.txt
omnigibson/action_primitives/action_primitive_set_base.py
omnigibson/action_primitives/curobo.py
omnigibson/action_primitives/starter_semantic_action_primitives.py
omnigibson/action_primitives/symbolic_semantic_action_primitives.py
omnigibson/configs/default_cfg.yaml
omnigibson/configs/fetch_behavior.yaml
omnigibson/configs/fetch_primitives.yaml
omnigibson/configs/tiago_primitives.yaml
omnigibson/configs/turtlebot_nav.yaml
omnigibson/configs/controllers/dd.yaml
omnigibson/configs/controllers/ik.yaml
omnigibson/configs/controllers/joint.yaml
omnigibson/configs/controllers/multi_finger_gripper.yaml
omnigibson/configs/controllers/null_gripper.yaml
omnigibson/configs/robots/fetch.yaml
omnigibson/configs/robots/freight.yaml
omnigibson/configs/robots/husky.yaml
omnigibson/configs/robots/locobot.yaml
omnigibson/configs/robots/turtlebot.yaml
omnigibson/configs/sensors/scan.yaml
omnigibson/configs/sensors/vision.yaml
omnigibson/controllers/__init__.py
omnigibson/controllers/controller_base.py
omnigibson/controllers/dd_controller.py
omnigibson/controllers/ik_controller.py
omnigibson/controllers/joint_controller.py
omnigibson/controllers/multi_finger_gripper_controller.py
omnigibson/controllers/null_joint_controller.py
omnigibson/controllers/osc_controller.py
omnigibson/envs/__init__.py
omnigibson/envs/data_wrapper.py
omnigibson/envs/env_base.py
omnigibson/envs/env_wrapper.py
omnigibson/envs/sb3_vec_env.py
omnigibson/envs/vec_env_base.py
omnigibson/examples/__init__.py
omnigibson/examples/action_primitives/__init__.py
omnigibson/examples/action_primitives/rs_int_example.py
