Metadata-Version: 2.1
Name: omnigibson
Version: 1.1.1
Home-page: https://github.com/StanfordVL/OmniGibson
Author: Stanford University
Requires-Python: >=3
License-File: LICENSE
Requires-Dist: gymnasium>=0.28.1
Requires-Dist: numpy<2.0.0,>=1.23.5
Requires-Dist: scipy>=1.10.1
Requires-Dist: GitPython~=3.1.40
Requires-Dist: transforms3d~=0.4.1
Requires-Dist: networkx~=3.2.1
Requires-Dist: PyYAML~=6.0.1
Requires-Dist: addict~=2.4.0
Requires-Dist: ipython~=8.20.0
Requires-Dist: future~=0.18.3
Requires-Dist: trimesh~=4.0.8
Requires-Dist: h5py~=3.10.0
Requires-Dist: cryptography~=41.0.7
Requires-Dist: bddl~=3.5.0
Requires-Dist: opencv-python>=4.8.1
Requires-Dist: nest_asyncio~=1.5.8
Requires-Dist: imageio~=2.33.1
Requires-Dist: imageio-ffmpeg~=0.4.9
Requires-Dist: termcolor~=2.4.0
Requires-Dist: progressbar~=2.5
Requires-Dist: pymeshlab~=2022.2
Requires-Dist: click~=8.1.3
Requires-Dist: aenum~=3.1.15
Requires-Dist: rtree~=1.2.0
Requires-Dist: graphviz~=0.20
Requires-Dist: matplotlib>=3.0.0
